ans_vtk_extension/CxxEngine.dll
ans_vtk_extension/__init__.py
ans_vtk_extension/vtk.py
ans_vtk_extension/vtkChartsCore.dll
ans_vtk_extension/vtkCommonColor.dll
ans_vtk_extension/vtkCommonComputationalGeometry.dll
ans_vtk_extension/vtkCommonCore.dll
ans_vtk_extension/vtkCommonDataModel.dll
ans_vtk_extension/vtkCommonExecutionModel.dll
ans_vtk_extension/vtkCommonMath.dll
ans_vtk_extension/vtkCommonMisc.dll
ans_vtk_extension/vtkCommonSystem.dll
ans_vtk_extension/vtkCommonTransforms.dll
ans_vtk_extension/vtkDICOMParser.dll
ans_vtk_extension/vtkDomainsChemistry.dll
ans_vtk_extension/vtkDomainsChemistryOpenGL2.dll
ans_vtk_extension/vtkFiltersCellGrid.dll
ans_vtk_extension/vtkFiltersCore.dll
ans_vtk_extension/vtkFiltersExtraction.dll
ans_vtk_extension/vtkFiltersGeneral.dll
ans_vtk_extension/vtkFiltersGeometry.dll
ans_vtk_extension/vtkFiltersHybrid.dll
ans_vtk_extension/vtkFiltersHyperTree.dll
ans_vtk_extension/vtkFiltersImaging.dll
ans_vtk_extension/vtkFiltersModeling.dll
ans_vtk_extension/vtkFiltersReduction.dll
ans_vtk_extension/vtkFiltersSources.dll
ans_vtk_extension/vtkFiltersStatistics.dll
ans_vtk_extension/vtkFiltersTexture.dll
ans_vtk_extension/vtkFiltersVerdict.dll
ans_vtk_extension/vtkIOCellGrid.dll
ans_vtk_extension/vtkIOCore.dll
ans_vtk_extension/vtkIOExport.dll
ans_vtk_extension/vtkIOExportGL2PS.dll
ans_vtk_extension/vtkIOExportPDF.dll
ans_vtk_extension/vtkIOGeometry.dll
ans_vtk_extension/vtkIOImage.dll
ans_vtk_extension/vtkIOLegacy.dll
ans_vtk_extension/vtkIOXML.dll
ans_vtk_extension/vtkIOXMLParser.dll
ans_vtk_extension/vtkImagingColor.dll
ans_vtk_extension/vtkImagingCore.dll
ans_vtk_extension/vtkImagingGeneral.dll
ans_vtk_extension/vtkImagingHybrid.dll
ans_vtk_extension/vtkImagingMath.dll
ans_vtk_extension/vtkImagingSources.dll
ans_vtk_extension/vtkInfovisCore.dll
ans_vtk_extension/vtkInfovisLayout.dll
ans_vtk_extension/vtkInteractionImage.dll
ans_vtk_extension/vtkInteractionStyle.dll
ans_vtk_extension/vtkInteractionWidgets.dll
ans_vtk_extension/ans_vtk_extension.egg-info/PKG-INFO
ans_vtk_extension/ans_vtk_extension.egg-info/SOURCES.txt
ans_vtk_extension/ans_vtk_extension.egg-info/dependency_links.txt
ans_vtk_extension/ans_vtk_extension.egg-info/not-zip-safe
ans_vtk_extension/ans_vtk_extension.egg-info/top_level.txt
ans_vtk_extension-0.0.dist-info/LICENSE
ans_vtk_extension-0.0.dist-info/METADATA
ans_vtk_extension-0.0.dist-info/WHEEL
ans_vtk_extension-0.0.dist-info/top_level.txt
ans_vtk_extension-0.0.dist-info/RECORD
