Metadata-Version: 2.1
Name: ans-vtk-extension
Version: 0.0
Summary: C++ extension.
License-File: LICENSE
